{
	"red": ["#FFEDA0", "#FED976", "#FEB24C", "#FD8D3C", "#FC4E2A", "#E31A1C", "#BD0026", "#800026"],
	"blue": ["#ffffd9", "#edf8b1", "#c7e9b4", "#7fcdbb", "#41b6c4", "#1d91c0", "#225ea8", "#0c2c84"],
	"green": ["#f7fcfd", "#e5f5f9", "#ccece6", "#99d8c9", "#66c2a4", "#41ae76", "#238b45", "#005824"],
	"purple": ["#fff7f3", "#fde0dd", "#fcc5c0", "#fa9fb5", "#f768a1", "#dd3497", "#ae017e", "#7a0177"],
	"green_red": ["#1a9850", "#66bd63", "#a6d96a", "#d9ef8b", "#fee08b", "#fdae61", "#f46d43", "#d73027"]
}